[
  {
    "id": 1,
    "name": "一元二次方程",
    "category": "代数",
    "description": "形如ax²+bx+c=0（a≠0）的方程，其中a、b、c是已知数，x是未知数",
    "grade_level": "初中二年级",
    "difficulty": 0.6,
    "prerequisites": ["代数基础", "一元一次方程", "多项式", "乘法公式"],
    "related_concepts": ["二次函数", "抛物线", "因式分解", "判别式", "韦达定理", "配方法", "根的分布", "代数恒等式", "二次不等式"],
    "key_points": [
      "一元二次方程的标准形式：ax²+bx+c=0（a≠0）",
      "求根公式：x = (-b ± √(b² - 4ac)) / 2a",
      "判别式：△ = b² - 4ac，△>0有两个不相等实根，△=0有两个相等实根，△<0没有实根",
      "韦达定理：x₁ + x₂ = -b/a，x₁ × x₂ = c/a",
      "因式分解法：ax² + bx + c = a(x - x₁)(x - x₂)",
      "配方法：ax² + bx + c = a(x + b/(2a))² + c - b²/(4a)"
    ],
    "common_errors": [
      "忘记判断a≠0的条件",
      "计算判别式时符号错误",
      "使用求根公式时计算错误",
      "因式分解时符号错误",
      "配方法使用不当"
    ],
    "examples": [
      {
        "problem": "解方程：x² - 5x + 6 = 0",
        "solution": "a=1, b=-5, c=6\n△=b²-4ac=(-5)²-4×1×6=25-24=1>0\n所以方程有两个不相等的实根\nx = (5 ± √1) / 2 = (5 ± 1) / 2\nx₁ = 3, x₂ = 2\n验证：3+2=5，3×2=6，符合韦达定理"
      },
      {
        "problem": "解方程：x² - 6x + 9 = 0",
        "solution": "a=1, b=-6, c=9\n△=b²-4ac=(-6)²-4×1×9=36-36=0\n所以方程有两个相等的实根\nx = 6/2 = 3\n验证：3+3=6，3×3=9，符合韦达定理"
      }
    ],
    "learning_resources": [
      {
        "title": "一元二次方程基础",
        "type": "video",
        "url": "/resources/algebra/quadratic_equations/basics"
      },
      {
        "title": "一元二次方程解法详解",
        "type": "article",
        "url": "/resources/algebra/quadratic_equations/methods"
      },
      {
        "title": "一元二次方程应用题",
        "type": "practice",
        "url": "/resources/algebra/quadratic_equations/applications"
      }
    ]
  },
  {
    "id": 2,
    "name": "三角形",
    "category": "几何",
    "description": "由三条线段首尾顺次连接而成的平面图形",
    "grade_level": "初中一年级",
    "difficulty": 0.5,
    "prerequisites": ["平面几何基础", "线段", "角度", "勾股定理"],
    "related_concepts": ["多边形", "角", "全等", "相似", "等腰三角形", "等边三角形", "直角三角形", "锐角三角形", "钝角三角形", "三角形中心", "三角不等式", "重心", "内心", "外心", "垂心", "中线", "角平分线", "高"],
    "key_points": [
      "三角形内角和为180°",
      "三角形外角等于与它不相邻的两个内角的和",
      "三角形任意两边之和大于第三边，任意两边之差小于第三边",
      "三角形的面积公式：S = (1/2)·底·高",
      "三角形的面积公式：S = (1/2)·ab·sinC（正弦公式）",
      "三角形的面积公式：S = √[s(s-a)(s-b)(s-c)]（海伦公式，其中s=(a+b+c)/2）",
      "三角形的中线：连接顶点与对边中点的线段",
      "三角形的角平分线：平分顶点角的射线",
      "三角形的高：从顶点向对边或对边的延长线作垂线"
    ],
    "common_errors": [
      "混淆内角和外角的概念",
      "计算面积时使用错误的公式",
      "不理解三角形的存在条件",
      "混淆中线、高和角平分线",
      "错误应用三角形的全等条件"
    ],
    "examples": [
      {
        "problem": "已知三角形的三边长分别为3cm、4cm和5cm，求该三角形的面积。",
        "solution": "使用海伦公式：\ns = (3+4+5)/2 = 6\nS = √[6(6-3)(6-4)(6-5)] = √[6×3×2×1] = √36 = 6\n所以三角形的面积为6平方厘米。"
      },
      {
        "problem": "已知三角形的底边长为8cm，高为5cm，求该三角形的面积。",
        "solution": "使用面积公式：S = (1/2)·底·高 = (1/2)×8×5 = 20\n所以三角形的面积为20平方厘米。"
      }
    ],
    "learning_resources": [
      {
        "title": "三角形的基本性质",
        "type": "video",
        "url": "/resources/geometry/triangle/basics"
      },
      {
        "title": "三角形的面积计算方法",
        "type": "article",
        "url": "/resources/geometry/triangle/area"
      },
      {
        "title": "三角形的判定与证明",
        "type": "practice",
        "url": "/resources/geometry/triangle/proofs"
      }
    ]
  },
  {
    "id": 3,
    "name": "等腰三角形",
    "category": "几何",
    "description": "有两条边相等的三角形",
    "grade_level": "初中一年级",
    "difficulty": 0.5,
    "prerequisites": ["三角形", "角度", "对称性"],
    "related_concepts": ["等边三角形", "直角三角形", "全等", "轴对称", "角平分线", "垂直平分线", "中线", "高", "三角形的五心", "等腰直角三角形"],
    "key_points": [
      "等腰三角形有两条边相等，这两条边叫做腰，第三边叫做底边",
      "等腰三角形的两个底角相等",
      "等腰三角形的顶角平分线、底边上的高、底边上的中线重合",
      "等腰三角形的面积公式：S = (1/2)·底·高",
      "等腰三角形具有轴对称性，对称轴是顶角平分线",
      "等腰三角形的判定：两边相等；两角相等；一个顶点到对边的距离平分对边"
    ],
    "common_errors": [
      "混淆等腰三角形和等边三角形",
      "忘记等腰三角形的特殊性质",
      "错误应用等腰三角形的判定定理",
      "忘记等腰三角形的对称性质"
    ],
    "examples": [
      {
        "problem": "等腰三角形的两条腰长为5cm，底边长为6cm，求该三角形的面积。",
        "solution": "设底边上的高为h，根据勾股定理：\n5² = (6/2)² + h²\n25 = 9 + h²\nh² = 16\nh = 4\n所以三角形的面积为：S = (1/2)×6×4 = 12平方厘米"
      },
      {
        "problem": "等腰三角形的两个底角各为45°，腰长为10cm，求该三角形的面积。",
        "solution": "顶角 = 180° - 45° - 45° = 90°\n这是一个等腰直角三角形\n底边长 = 2×10×sin45° = 2×10×(√2/2) = 10√2\n高 = 10×cos45° = 10×(√2/2) = 5√2\nS = (1/2)×10√2×5√2 = 50平方厘米"
      }
    ],
    "learning_resources": [
      {
        "title": "等腰三角形的性质",
        "type": "video",
        "url": "/resources/geometry/isosceles_triangle/properties"
      },
      {
        "title": "等腰三角形的判定方法",
        "type": "article",
        "url": "/resources/geometry/isosceles_triangle/identification"
      },
      {
        "title": "等腰三角形的应用题",
        "type": "practice",
        "url": "/resources/geometry/isosceles_triangle/applications"
      }
    ]
  },
  {
    "id": 4,
    "name": "圆",
    "category": "几何",
    "description": "平面上到定点（圆心）距离相等的所有点的集合",
    "grade_level": "初中二年级",
    "difficulty": 0.6,
    "prerequisites": ["平面几何基础", "线段", "角", "距离", "π"],
    "related_concepts": ["圆周率", "弧", "弦", "扇形", "圆环", "弓形", "切线", "割线", "圆心角", "圆周角", "内接多边形", "外接多边形", "内切圆", "外接圆", "圆的方程", "椭圆"],
    "key_points": [
      "圆的半径：从圆心到圆上任意一点的线段",
      "圆的直径：过圆心且端点在圆上的线段，等于2倍半径",
      "圆的周长公式：C = 2πr",
      "圆的面积公式：S = πr²",
      "圆心角的度数等于它所对的弧所对的圆周角的2倍",
      "半圆内的圆周角是直角",
      "圆的切线垂直于过切点的半径",
      "同圆或等圆中，相等的圆心角所对的弧相等",
      "扇形面积公式：S = (θ/360°)·πr²，其中θ为圆心角的度数"
    ],
    "common_errors": [
      "混淆圆的周长和面积公式",
      "计算时π的取值不一致",
      "圆周角定理应用错误",
      "切线性质理解错误",
      "弧长计算错误"
    ],
    "examples": [
      {
        "problem": "一个圆的半径为5cm，求该圆的周长和面积。（取π=3.14）",
        "solution": "周长 = 2πr = 2×3.14×5 = 31.4cm\n面积 = πr² = 3.14×5² = 3.14×25 = 78.5平方厘米"
      },
      {
        "problem": "如果一个圆的面积是28.26平方厘米，求该圆的半径和周长。（取π=3.14）",
        "solution": "面积 = πr²\n28.26 = 3.14×r²\nr² = 28.26 ÷ 3.14 = 9\nr = 3cm\n周长 = 2πr = 2×3.14×3 = 18.84cm"
      }
    ],
    "learning_resources": [
      {
        "title": "圆的基本性质",
        "type": "video",
        "url": "/resources/geometry/circle/basics"
      },
      {
        "title": "圆的周长与面积",
        "type": "article",
        "url": "/resources/geometry/circle/area_and_perimeter"
      },
      {
        "title": "圆的切线性质",
        "type": "practice",
        "url": "/resources/geometry/circle/tangent"
      }
    ]
  },
  {
    "id": 5,
    "name": "集合",
    "category": "集合论",
    "description": "具有某种特定性质的事物的总体",
    "grade_level": "初中三年级",
    "difficulty": 0.7,
    "prerequisites": ["基础数学概念", "逻辑关系"],
    "related_concepts": ["元素", "子集", "空集", "全集", "交集", "并集", "补集", "差集", "对称差", "文氏图", "集合的势", "幂集", "有序对", "笛卡尔积", "集合的运算律", "集合的应用", "命题逻辑"],
    "key_points": [
      "集合的表示法：列举法和描述法",
      "集合的基本运算：并集、交集、补集、差集",
      "并集：A∪B = {x|x∈A或x∈B}",
      "交集：A∩B = {x|x∈A且x∈B}",
      "补集：A' = {x|x∈U且x∉A}，其中U为全集",
      "差集：A-B = {x|x∈A且x∉B}",
      "德摩根律：(A∪B)' = A'∩B'，(A∩B)' = A'∪B'",
      "分配律：A∩(B∪C) = (A∩B)∪(A∩C)，A∪(B∩C) = (A∪B)∩(A∪C)"
    ],
    "common_errors": [
      "混淆并集和交集的概念",
      "集合运算顺序错误",
      "不理解空集的性质",
      "错误应用德摩根律",
      "集合表示法使用不当"
    ],
    "examples": [
      {
        "problem": "已知集合A={1,2,3,4,5}，B={3,4,5,6,7}，求A∪B、A∩B和A-B。",
        "solution": "A∪B = {1,2,3,4,5,6,7}\nA∩B = {3,4,5}\nA-B = {1,2}"
      },
      {
        "problem": "已知全集U={1,2,3,4,5,6,7,8,9,10}，集合A={2,4,6,8,10}，B={1,3,5,7,9}，求A'和A∩B。",
        "solution": "A' = {1,3,5,7,9}\nA∩B = ∅（空集）"
      }
    ],
    "learning_resources": [
      {
        "title": "集合的基本概念",
        "type": "video",
        "url": "/resources/set_theory/basics"
      },
      {
        "title": "集合的运算",
        "type": "article",
        "url": "/resources/set_theory/operations"
      },
      {
        "title": "集合的应用",
        "type": "practice",
        "url": "/resources/set_theory/applications"
      }
    ]
  },
  {
    "id": 6,
    "name": "统计与概率基础",
    "category": "统计",
    "description": "研究数据收集、整理、分析和解释的数学分支",
    "grade_level": "初中三年级",
    "difficulty": 0.6,
    "prerequisites": ["基础数学", "分数", "百分比", "集合论"],
    "related_concepts": ["平均值", "中位数", "众数", "方差", "标准差", "四分位数", "极差", "频率", "频率分布表", "茎叶图", "直方图", "箱线图", "散点图", "相关系数", "回归分析", "概率", "古典概型", "几何概型", "条件概率", "独立事件", "贝叶斯定理", "随机变量", "期望值", "二项分布", "正态分布"],
    "key_points": [
      "平均值：总和除以数量",
      "中位数：按大小排序后居于中间的数",
      "众数：出现次数最多的数",
      "极差：最大值减最小值",
      "方差：各数据与平均值的差的平方的平均值",
      "标准差：方差的算术平方根",
      "概率：特定事件发生的可能性，值在0到1之间",
      "古典概型：等可能事件的概率 = 有利事件数 / 总事件数",
      "条件概率：P(A|B) = P(A∩B) / P(B)",
      "独立事件：P(A∩B) = P(A)·P(B)"
    ],
    "common_errors": [
      "计算平均值时分子分母错误",
      "找中位数时忘记排序",
      "概率计算时分子分母定义错误",
      "混淆独立事件和互斥事件",
      "条件概率应用错误"
    ],
    "examples": [
      {
        "problem": "一组数据：2, 5, 7, 5, 8, 10, 5，求这组数据的平均值、中位数和众数。",
        "solution": "平均值 = (2+5+7+5+8+10+5)/7 = 42/7 = 6\n排序后：2, 5, 5, 5, 7, 8, 10\n中位数 = 5\n众数 = 5（出现3次）"
      },
      {
        "problem": "从一副标准扑克牌（52张）中随机抽一张牌，求抽到红桃的概率。",
        "solution": "红桃有13张，总共52张\n概率 = 13/52 = 1/4 = 0.25 = 25%"
      }
    ],
    "learning_resources": [
      {
        "title": "统计学基础概念",
        "type": "video",
        "url": "/resources/statistics/basics"
      },
      {
        "title": "数据分析方法",
        "type": "article",
        "url": "/resources/statistics/data_analysis"
      },
      {
        "title": "概率计算与应用",
        "type": "practice",
        "url": "/resources/statistics/probability"
      }
    ]
  },
  {
    "id": 7,
    "name": "二次函数",
    "category": "代数",
    "description": "形如f(x)=ax²+bx+c（a≠0）的函数",
    "grade_level": "初中三年级",
    "difficulty": 0.7,
    "prerequisites": ["函数基础", "一元二次方程", "坐标系"],
    "related_concepts": ["抛物线", "顶点", "对称轴", "函数图像", "函数零点", "最值", "单调性", "二次不等式", "配方法", "待定系数法", "函数变换", "函数应用", "二次规划"],
    "key_points": [
      "二次函数的标准形式：f(x)=ax²+bx+c（a≠0）",
      "二次函数的顶点式：f(x)=a(x-h)²+k，其中(h,k)为顶点坐标",
      "二次函数的图像是抛物线",
      "当a>0时，抛物线开口向上，函数有最小值；当a<0时，抛物线开口向下，函数有最大值",
      "抛物线的对称轴方程：x=-b/(2a)",
      "抛物线的顶点坐标：(-b/(2a), f(-b/(2a)))",
      "二次函数的零点与对应的一元二次方程的根相同"
    ],
    "common_errors": [
      "判断开口方向时符号错误",
      "计算顶点坐标时公式使用错误",
      "绘制图像时对称性理解不清",
      "求最值时方法不当",
      "函数与方程关系混淆"
    ],
    "examples": [
      {
        "problem": "求函数f(x)=2x²-4x+3的顶点坐标和最小值。",
        "solution": "a=2, b=-4, c=3\n对称轴：x=-b/(2a)=-(-4)/(2×2)=1\n顶点的x坐标为1\n顶点的y坐标：f(1)=2×1²-4×1+3=2-4+3=1\n所以顶点坐标为(1,1)，最小值为1"
      },
      {
        "problem": "已知二次函数f(x)=ax²+bx+c的图像过点(0,3)、(1,0)、(2,1)，求该函数的解析式。",
        "solution": "代入点(0,3)：f(0)=a×0²+b×0+c=c=3\n代入点(1,0)：f(1)=a×1²+b×1+c=a+b+c=0\n代入点(2,1)：f(2)=a×2²+b×2+c=4a+2b+c=1\n得到方程组：\nc=3\na+b+c=0\n4a+2b+c=1\n解得：a=2, b=-5, c=3\n所以函数解析式为f(x)=2x²-5x+3"
      }
    ],
    "learning_resources": [
      {
        "title": "二次函数的基本概念",
        "type": "video",
        "url": "/resources/algebra/quadratic_functions/basics"
      },
      {
        "title": "二次函数的图像与性质",
        "type": "article",
        "url": "/resources/algebra/quadratic_functions/properties"
      },
      {
        "title": "二次函数的应用",
        "type": "practice",
        "url": "/resources/algebra/quadratic_functions/applications"
      }
    ]
  },
  {
    "id": 8,
    "name": "三角函数",
    "category": "三角学",
    "description": "研究角度（或弧度）与直角三角形边长比值之间关系的函数",
    "grade_level": "高中一年级",
    "difficulty": 0.8,
    "prerequisites": ["角度与弧度", "直角三角形", "坐标系", "函数概念"],
    "related_concepts": ["正弦", "余弦", "正切", "余切", "正割", "余割", "单位圆", "周期性", "三角恒等式", "和角公式", "倍角公式", "半角公式", "和差化积", "积化和差", "三角方程", "反三角函数", "三角函数图像", "振幅", "相位", "频率", "三角变换"],
    "key_points": [
      "基本三角函数：正弦(sin)、余弦(cos)、正切(tan)",
      "单位圆定义：在单位圆上，角θ对应点的坐标为(cosθ, sinθ)",
      "基本三角恒等式：sin²θ + cos²θ = 1",
      "正切定义：tanθ = sinθ / cosθ",
      "正弦余弦的周期为2π，正切的周期为π",
      "特殊角的三角函数值：0°, 30°, 45°, 60°, 90°",
      "和角公式：sin(α+β) = sinα·cosβ + cosα·sinβ",
      "和角公式：cos(α+β) = cosα·cosβ - sinα·sinβ",
      "二倍角公式：sin2α = 2sinα·cosα",
      "二倍角公式：cos2α = cos²α - sin²α = 2cos²α - 1 = 1 - 2sin²α"
    ],
    "common_errors": [
      "角度与弧度混淆",
      "特殊角三角函数值记忆错误",
      "三角恒等式应用不当",
      "周期性理解错误",
      "符号判断错误"
    ],
    "examples": [
      {
        "problem": "计算：sin30° + cos60° + tan45°",
        "solution": "sin30° = 1/2\ncos60° = 1/2\ntan45° = 1\n所以sin30° + cos60° + tan45° = 1/2 + 1/2 + 1 = 2"
      },
      {
        "problem": "化简：sin²α + cos²α",
        "solution": "根据三角恒等式：sin²α + cos²α = 1"
      }
    ],
    "learning_resources": [
      {
        "title": "三角函数的基本概念",
        "type": "video",
        "url": "/resources/trigonometry/basics"
      },
      {
        "title": "三角恒等式",
        "type": "article",
        "url": "/resources/trigonometry/identities"
      },
      {
        "title": "三角函数的应用",
        "type": "practice",
        "url": "/resources/trigonometry/applications"
      }
    ]
  }
] 